faff/__init__.py
faff/__main__.py
faff/core.py
faff/exceptions.py
faff/include.py
faff/main.py
faff/option.py
faff/rule.py
faff/run.py
faff/targets.py
faff/variable.py
faff/ext/__init__.py
faff/ext/changelog.py
faff/ext/exceptions.py
faff/ext/compilers/__init__.py
faff/ext/compilers/gcc.py
faff/ext/templates/CHANGELOG.md
faff/ext/templates/CHANGELOG.rst
faff-0.2.4.dist-info/DESCRIPTION.rst
faff-0.2.4.dist-info/METADATA
faff-0.2.4.dist-info/RECORD
faff-0.2.4.dist-info/WHEEL
faff-0.2.4.dist-info/entry_points.txt
faff-0.2.4.dist-info/metadata.json
faff-0.2.4.dist-info/top_level.txt
