Metadata-Version: 2.0
Name: faff
Version: 0.2.4
Summary: Make build tool substitute written in Python.
Home-page: https://github.com/mojzu/faff
Author: mojzu
Author-email: mail@mojzu.net
License: Public Domain
Platform: UNKNOWN
Classifier: Development Status :: 3 - Alpha
Classifier: Intended Audience :: Developers
Classifier: License :: Public Domain
Classifier: Programming Language :: Python :: 3.5
Classifier: Topic :: Software Development :: Build Tools
Requires-Dist: Jinja2 (>=2.8)
Requires-Dist: colorama (>=0.3.7)
